story/__init__.py
story/api.py
story/awesome.py
story/cli.py
story/ensure.py
story/environment.py
story/main.py
story/options.py
story/storage.py
story/support.py
story/utils.py
story/version.py
story/commands/__init__.py
story/commands/apps.py
story/commands/completion.py
story/commands/config.py
story/commands/deploy.py
story/commands/feedback.py
story/commands/login.py
story/commands/logs.py
story/commands/maintenance.py
story/commands/releases.py
story/commands/run.py
story/commands/status.py
story/commands/test.py
story/commands/update.py
story/commands/write.py
story/commands/repl/Repl.py
story/commands/repl/Scope.py
story/commands/repl/__init__.py
story/helpers/__init__.py
story/helpers/datetime.py
story/helpers/didyoumean.py
story/stories/function.story
story/stories/http.story
story/stories/if.story
story/stories/loop.story
story/stories/slack-bot.story
story-0.17.1.dist-info/LICENSE
story-0.17.1.dist-info/METADATA
story-0.17.1.dist-info/WHEEL
story-0.17.1.dist-info/entry_points.txt
story-0.17.1.dist-info/top_level.txt
story-0.17.1.dist-info/zip-safe
story-0.17.1.dist-info/RECORD
