Metadata-Version: 2.1
Name: story
Version: 0.17.1
Summary: Storyscript Cloud CLI
Home-page: https://docs.storyscript.io/cli
Author: Storyscript
Author-email: hello@storyscript.io
License: Apache 2
Download-URL: https://github.com/storyscript/cli/archive/0.17.1.zip
Keywords: storyscript devops devtools microservices orchestration serverless APIs asyncy
Platform: UNKNOWN
Classifier: Development Status :: 3 - Alpha
Classifier: Environment :: Console
Classifier: Intended Audience :: Developers
Classifier: Intended Audience :: System Administrators
Classifier: License :: OSI Approved :: MIT License
Classifier: Natural Language :: English
Classifier: Programming Language :: Python :: 3.7
Classifier: Topic :: Office/Business
Classifier: Topic :: Software Development :: Build Tools
Requires-Dist: asyncio (>=3.4.3)
Requires-Dist: click-completion (==0.5.1)
Requires-Dist: click-help-colors (==0.5)
Requires-Dist: click-spinner (==0.1.8)
Requires-Dist: click (==7.0)
Requires-Dist: emoji (==0.5.0)
Requires-Dist: raven (==6.9.0)
Requires-Dist: requests (>=2.20.0)
Requires-Dist: storyscript (==0.20.1)
Requires-Dist: websockets (>=7.0)
Requires-Dist: texttable (>=1.4.0)
Requires-Dist: pyyaml (>=4.2)
Requires-Dist: pytz (>=2018.5)
Requires-Dist: blindspin
Requires-Dist: appdirs
Requires-Dist: xerox
Requires-Dist: semver
